py_dbt_cll/__init__.py
py_dbt_cll/dbt_lineage.py
py_dbt_cll-0.1.3.dist-info/METADATA
py_dbt_cll-0.1.3.dist-info/WHEEL
py_dbt_cll-0.1.3.dist-info/RECORD
